ap_donnes_des_sous/__init__.py
ap_donnes_des_sous/banque.py
ap_donnes_des_sous-0.1.1.dist-info/WHEEL
ap_donnes_des_sous-0.1.1.dist-info/entry_points.txt
ap_donnes_des_sous-0.1.1.dist-info/METADATA
ap_donnes_des_sous-0.1.1.dist-info/RECORD
